ucnumber/__init__.py
ucnumber-0.1.2.dist-info/LICENSE
ucnumber-0.1.2.dist-info/METADATA
ucnumber-0.1.2.dist-info/WHEEL
ucnumber-0.1.2.dist-info/top_level.txt
ucnumber-0.1.2.dist-info/RECORD
