Metadata-Version: 2.1
Name: ucnumber
Version: 0.1.2
Summary: Validate UC alumni identifier numbers.
Home-page: https://github.com/mrpatiwi/uc-numero-alumno-python
Author: Patricio López
Author-email: patricio@lopezjuri.com
License: MIT
Keywords: uc,puc,chile,numero,alumno
Platform: UNKNOWN
License-File: LICENSE
